README.rst
setup.py
src/vcstools/__init__.py
src/vcstools/__version__.py
src/vcstools/bzr.py
src/vcstools/common.py
src/vcstools/git.py
src/vcstools/git_archive_all.py
src/vcstools/hg.py
src/vcstools/svn.py
src/vcstools/tar.py
src/vcstools/vcs_abstraction.py
src/vcstools/vcs_base.py
src/vcstools_latest.egg-info/PKG-INFO
src/vcstools_latest.egg-info/SOURCES.txt
src/vcstools_latest.egg-info/dependency_links.txt
src/vcstools_latest.egg-info/requires.txt
src/vcstools_latest.egg-info/top_level.txt
test/test_base.py
test/test_bzr.py
test/test_code_format.py
test/test_git.py
test/test_git_subm.py
test/test_hg.py
test/test_svn.py
test/test_tar.py
test/test_vcs_abstraction.py